vision_chain/ensemble.py
vision_chain/hparam_tuner.py
vision_chain/model.py
vision_chain/postprocessing.py
vision_chain/predictions.py
vision_chain/split_dataset.py
vision_chain-0.0.1.dist-info/LICENSE
vision_chain-0.0.1.dist-info/METADATA
vision_chain-0.0.1.dist-info/WHEEL
vision_chain-0.0.1.dist-info/top_level.txt
vision_chain-0.0.1.dist-info/RECORD
